odoo/addons/stock_account_inventory_force_date/README.rst
odoo/addons/stock_account_inventory_force_date/__init__.py
odoo/addons/stock_account_inventory_force_date/__manifest__.py
odoo/addons/stock_account_inventory_force_date/i18n/it.po
odoo/addons/stock_account_inventory_force_date/i18n/sl.po
odoo/addons/stock_account_inventory_force_date/i18n/stock_account_inventory_force_date.pot
odoo/addons/stock_account_inventory_force_date/models/__init__.py
odoo/addons/stock_account_inventory_force_date/models/res_company.py
odoo/addons/stock_account_inventory_force_date/models/stock_inventory.py
odoo/addons/stock_account_inventory_force_date/models/stock_inventory_line.py
odoo/addons/stock_account_inventory_force_date/models/stock_move.py
odoo/addons/stock_account_inventory_force_date/models/stock_move_line.py
odoo/addons/stock_account_inventory_force_date/readme/CONTRIBUTORS.rst
odoo/addons/stock_account_inventory_force_date/readme/DESCRIPTION.rst
odoo/addons/stock_account_inventory_force_date/security/stock_account_inventory_force_date_security.xml
odoo/addons/stock_account_inventory_force_date/static/description/icon.png
odoo/addons/stock_account_inventory_force_date/static/description/index.html
odoo/addons/stock_account_inventory_force_date/tests/__init__.py
odoo/addons/stock_account_inventory_force_date/tests/test_stock_inventory_force_date.py
odoo/addons/stock_account_inventory_force_date/views/res_company_view.xml
odoo/addons/stock_account_inventory_force_date/views/stock_inventory_view.xml
odoo12_addon_stock_account_inventory_force_date-12.0.1.0.2.dist-info/METADATA
odoo12_addon_stock_account_inventory_force_date-12.0.1.0.2.dist-info/WHEEL
odoo12_addon_stock_account_inventory_force_date-12.0.1.0.2.dist-info/top_level.txt
odoo12_addon_stock_account_inventory_force_date-12.0.1.0.2.dist-info/RECORD
